lisq-2025.9.1.dist-info/licenses/LICENSE
src/__init__.py
src/colors.py
src/lisq.py
lisq-2025.9.1.dist-info/METADATA
lisq-2025.9.1.dist-info/WHEEL
lisq-2025.9.1.dist-info/entry_points.txt
lisq-2025.9.1.dist-info/top_level.txt
lisq-2025.9.1.dist-info/RECORD
