Metadata-Version: 2.4
Name: lisq
Version: 2025.9.1
Summary: A single file note-taking app that work with .txt files
Home-page: https://github.com/funnut/Lisq
Author: funnut
Author-email: essdoem@yahoo.com
License: Non-Commercial
Project-URL: Bug Tracker, https://github.com/funnut/Lisq/issues
Project-URL: Source Code, https://github.com/funnut/Lisq
Classifier: Programming Language :: Python :: 3
Classifier: License :: Other/Proprietary License
Classifier: Operating System :: OS Independent
Requires-Python: >=3.6
License-File: LICENSE
Requires-Dist: cryptography==45.0.6
Dynamic: author
Dynamic: author-email
Dynamic: classifier
Dynamic: description
Dynamic: description-content-type
Dynamic: home-page
Dynamic: license
Dynamic: license-file
Dynamic: project-url
Dynamic: requires-dist
Dynamic: requires-python
Dynamic: summary
